freeplane_and_yaml/__init__.py
freeplane_and_yaml/cli.py
freeplane_and_yaml/convert.py
freeplane_and_yaml/convert_pdf_to_mindmap.py
freeplane_and_yaml/llm_adapter.py
freeplane_and_yaml/openai_adapter.py
freeplane_and_yaml/pdf2mindmap.py
freeplane_and_yaml/text_to_mindmap.py
freeplane_and_yaml/yaml_utils.py
freeplane_and_yaml/schema/mindmap-schema.json
freeplane_and_yaml-0.3.0.dist-info/LICENSE
freeplane_and_yaml-0.3.0.dist-info/METADATA
freeplane_and_yaml-0.3.0.dist-info/WHEEL
freeplane_and_yaml-0.3.0.dist-info/entry_points.txt
freeplane_and_yaml-0.3.0.dist-info/top_level.txt
freeplane_and_yaml-0.3.0.dist-info/RECORD
