Metadata-Version: 2.1
Name: freeplane-and-yaml
Version: 0.3.0
Summary: A tool to convert PDF files to Freeplane mind maps using OpenAI
Home-page: https://github.com/romilly/freeplane-and-yaml
Author: Romilly Cocking
Author-email: romilly.cocking@gmail.com
License: MIT
Platform: UNKNOWN
Classifier: Programming Language :: Python :: 3
Classifier: License :: OSI Approved :: MIT License
Classifier: Operating System :: OS Independent
Requires-Python: >=3.9
License-File: LICENSE
Requires-Dist: PyYAML
Requires-Dist: openai
Requires-Dist: pymupdf4llm
Requires-Dist: python-dotenv
